Metadata-Version: 2.1
Name: flipfloperator
Version: 0.1.1
Summary: Sorry.
Home-page: UNKNOWN
Author: Peter Ward
Author-email: peteraward@gmail.com
License: UNKNOWN
Platform: UNKNOWN
